{
  "$id": "https://mapcolonies.com/three_d/fileSyncer/v1",
  "description": "The file-syncer schema",
  "$schema": "http://json-schema.org/draft-07/schema#",
  "type": "object",
  "required": ["jobManager", "source", "destination"],
  "allOf": [
    {
      "$ref": "https://mapcolonies.com/common/boilerplate/v4"
    },
    {
      "type": "object",
      "properties": {
        "jobManager": {
          "type": "object",
          "$ref": "https://mapcolonies.com/three_d/common/jobManager/v1",
          "required": ["task", "job", "url", "heartbeat"]
        }
      }
    },
    {
      "type": "object",
      "description": "I can't set the source and destination under storage. The file-syncer doesn't get the schema",
      "properties": {
        "source": {
          "$ref": "#/definitions/provider"
        },
        "destination": {
          "$ref": "#/definitions/provider"
        }
      },
      "$comment": "TODO: solves the duplicate refs block issue"
    },
    {
      "type": "object",
      "properties": {
        "intervalMs": {
          "type": "number",
          "description": "Cron-Job interval in milliseconds for polling task attempt",
          "default": 5000
        },
        "taskPoolSize": {
          "type": "number",
          "description": "How many task the service will fetch and process in an interval",
          "default": 5
        }
      }
    }
  ],
  "definitions": {
    "provider": {
      "$ref": "https://mapcolonies.com/three_d/common/provider/v1"
    }
  }
}
